news_law_mcp/__init__.py
news_law_mcp/__main__.py
news_law_mcp/prompts.py
check_news_law_mcp-0.1.2.dist-info/METADATA
check_news_law_mcp-0.1.2.dist-info/WHEEL
check_news_law_mcp-0.1.2.dist-info/top_level.txt
check_news_law_mcp-0.1.2.dist-info/RECORD
