Metadata-Version: 2.4
Name: check-news-law-mcp
Version: 0.1.2
Summary: Add your description here
Requires-Python: >=3.10
Requires-Dist: mcp[cli]>=1.7.1
Requires-Dist: openai>=1.77.0
